# 常量池

***

Java中常量池主要有**Class常量池（静态常量池、Constant pool）**、**运行时常量池**、**字符串常量池** 。

## Class常量池

虚拟机必须为每个被装载的类型维护一个常量池。常量池就是该类型所用常量的一个有序集合，包括直接常量（String ,integer和floating point常量）和对其他类型、字段和方法的符号引用。池中的数据项就像数组一样是通过索引访问的。**常量池存储了相应类型所用到的所有类型、字段和方法的符号引用**，所以它在Java程序的动态连接中起着核心作用。

Java虚拟机把常量池组织为入口列表的形式。

每个常量池入口都从一个长度为一个字节的标志开始，这个标志指出了列表中该位置的常量类型。一旦java虚拟机获取并解析这个标志，Java虚拟机就会知道在标志后的常量类型是什么。



Constant pool tags

| Entry Type                  | Tag Value | Description                              |
| --------------------------- | --------- | ---------------------------------------- |
| CONSTANT_Utf8               | 1         | A UTF-8 encoded Unicode string           |
| CONSTANT_Integer            | 3         | An int literal value                     |
| CONSTANT_Float              | 4         | A float literal value                    |
| CONSTANT_Long               | 5         | A long literal value                     |
| CONSTANT_Double             | 6         | A double literal value                   |
| CONSTANT_Class              | 7         | A symbolic reference to a class or interface |
| CONSTANT_String             | 8         | A String literal value                   |
| CONSTANT_Fieldref           | 9         | A symbolic reference to a field          |
| CONSTANT_Methodref          | 10        | A symbolic reference to a method declared in a class |
| CONSTANT_InterfaceMethodref | 11        | A symbolic reference to a method declared in an  interface |
| CONSTANT_NameAndType        | 12        | Part of a symbolic reference to a field or method |

表中的每一个标志都有一个相对应的表，表名通过在标志后加上“_info”后缀来产生。例如，对应于CONSTANT_Class标志的表名为CONSTANT_Class_info，表名为CONSTANT_Utf8_info的表中存储着Unicode字符串的压缩形式。对英语各种不同常量池入口的表将在本章后面详细描述。

在动态链接的Java程序中，常量池充当了十分重要的角色。除了字面常量（或者说直接量）值以外，常量池还可以容纳下面几种符号引用。

- 类和字段的全限定名，字段是类或接口的实例变量或者类变量；
- 字段的名称和描述符，字段的描述符是一个指示字段的类型的字符串；
- 方法的名称和描述符，方法的描述符也是一个字符串，该字符串指示方法的返回值和参数的数量，顺序和类型。

在运行时，Java虚拟机使用常量池的全限定名，方法和字段的描述符，把当前类或接口中的代码与其他类或接口中的代码连接起来。由于class文件并不包含其内部组件最终内存布局的信息，因此类，字段和方法并不能被class文件中的字节码直接引用。Java虚拟机从常量池获得符号引用，然后在运行时解析引用项的实际地址。


查看class文件

```sh
 javap -v XX.class
```

Java文件

```java
public class Main {
    public static void main(String[] args) {
        String s1 = "12342";
    }
    @Override
    public String toString() {
        return super.toString();
    }
}
```

class文件反编译

```sh
Classfile /E:/code/javatest/target/classes/Main.class
  Last modified 2023-4-21; size 514 bytes
  MD5 checksum 7423eea792b3a4dad80ce1fc77a151d4
  Compiled from "Main.java"
public class Main
  minor version: 0
  major version: 52
  flags: ACC_PUBLIC, ACC_SUPER
Constant pool:
   #1 = Methodref          #5.#23         // java/lang/Object."<init>":()V
   #2 = String             #24            // 12342
   #3 = Methodref          #5.#25         // java/lang/Object.toString:()Ljava/lang/String;
   #4 = Class              #26            // Main
   #5 = Class              #27            // java/lang/Object
   #6 = Utf8               <init>
   #7 = Utf8               ()V
   #8 = Utf8               Code
   #9 = Utf8               LineNumberTable
  #10 = Utf8               LocalVariableTable
  #11 = Utf8               this
  #12 = Utf8               LMain;
  #13 = Utf8               main
  #14 = Utf8               ([Ljava/lang/String;)V
  #15 = Utf8               args
  #16 = Utf8               [Ljava/lang/String;
  #17 = Utf8               s1
  #18 = Utf8               Ljava/lang/String;
  #19 = Utf8               toString
  #20 = Utf8               ()Ljava/lang/String;
  #21 = Utf8               SourceFile
  #22 = Utf8               Main.java
  #23 = NameAndType        #6:#7          // "<init>":()V
  #24 = Utf8               12342
  #25 = NameAndType        #19:#20        // toString:()Ljava/lang/String;
  #26 = Utf8               Main
  #27 = Utf8               java/lang/Object
{
  public Main();
    descriptor: ()V
    flags: ACC_PUBLIC
    Code:
      stack=1, locals=1, args_size=1
         0: aload_0
         1: invokespecial #1                  // Method java/lang/Object."<init>":()V
         4: return
      LineNumberTable:
        line 5: 0
      LocalVariableTable:
        Start  Length  Slot  Name   Signature
            0       5     0  this   LMain;

  public static void main(java.lang.String[]);
    descriptor: ([Ljava/lang/String;)V
    flags: ACC_PUBLIC, ACC_STATIC
    Code:
      stack=1, locals=2, args_size=1
         0: ldc           #2                  // String 12342
         2: astore_1
         3: return
      LineNumberTable:
        line 7: 0
        line 8: 3
      LocalVariableTable:
        Start  Length  Slot  Name   Signature
            0       4     0  args   [Ljava/lang/String;
            3       1     1    s1   Ljava/lang/String;

  public java.lang.String toString();
    descriptor: ()Ljava/lang/String;
    flags: ACC_PUBLIC
    Code:
      stack=1, locals=1, args_size=1
         0: aload_0
         1: invokespecial #3                  // Method java/lang/Object.toString:()Ljava/lang/String;
         4: areturn
      LineNumberTable:
        line 12: 0
      LocalVariableTable:
        Start  Length  Slot  Name   Signature
            0       5     0  this   LMain;
}
SourceFile: "Main.java"

```



## 字符串常量池

字符串常量池**存储的是 String 对象的直接引用或者对象**，是一张 `string table` ，底层基于HashMap实现。

> 字符串常量池原本存放于方法区，JDK7 开始放置于堆中。

用到时才会创建，当执行`String s1 = "abc"` 时，会先去串池中找是否存在字符串对象`abc`，如果存在直接返回引用；如果不存在会先在池中创建对象，再返回引用。

编译器会对一些代码优化，如

```java
String s1 = "ab";
String s2 = "a" + "b";
```

编译期间的优化，`s2`在编译期间已经能确定为`ab` ,在编译期间能确定的结果直接优化。

```sh
         0: ldc           #2                  // String ab
         2: astore_1
         3: ldc           #2                  // String ab
         5: astore_2
```

### intern

串池中只存放字符串常量的引用，动态拼接的字符串对象放在堆中，如。

```java
String s = new String("a") + new String("b");
//串池["a","b"],没有"ab"
//对象"ab"放在堆中
```

`intern`将这个字符串对象引用尝试放入串池，如果有则并不会放入；如果没有则放入串池， 再把串池中的对象引用返回。

```java
String s1 = "ab";
String s2 = new String("a") + new String("b");
String s3 =  s2.intern(); //放入串池，并返回
System.out.println(s1 == s2); 
System.out.println(s1 == s3);
//结果
false
true
```

### StringTable垃圾回收

字符串常量中的对象如果没有被引用也可以被垃圾回收。

## 运行时常量池

常量池中的信息，在运行时都会加载运行常量池中，只有具体执行到引用那一行代码时才会变成对象。